tests/__init__.py
tests/test_csv.py
tests/test_wrongtype.py
vinegar/__init__.py
vinegar/vinegar.py
vinegar-1.0.dist-info/METADATA
vinegar-1.0.dist-info/WHEEL
vinegar-1.0.dist-info/entry_points.txt
vinegar-1.0.dist-info/top_level.txt
vinegar-1.0.dist-info/RECORD
