Metadata-Version: 2.1
Name: vinegar
Version: 1.0
Summary: CLI to convert data into pickled pandas DataFrames.
License: UNKNOWN
Platform: UNKNOWN
Requires-Dist: pip (>=9)
Requires-Dist: setuptools (>=26)
Requires-Dist: twine
Requires-Dist: wheel (>=0.29)
Requires-Dist: numpy
Requires-Dist: pandas
Requires-Dist: black
Requires-Dist: coverage
Requires-Dist: flake8
Requires-Dist: pytest
Requires-Dist: yapf
